{"igrac-twap_sids_legal_qlt_obligstudies": {"data": {"recentValue": {}, "recentYear": {}}, "def": "", "name": "Obligatory studies on groundwater quality protection (Q.SD)", "source": "", "dataset": "", "category": "Characteristic", "subcategory": "None", "link": "https://staging.igrac.kartoza.com/layers/twap_public:twap_sids_legal_qlt_obligstudies", "dim": "", "priority": "2.0", "units": "nan"}, "confidenceIntervals": {"recentValue": {}}, "featureImportances": {"indicators": {"itu-fbs2": 0.142, "hdr-117906": 0.407, "unicef-ch15": 0.392, "ihme-urinary-tract-infections-and-interstitial-nephritis": 0.838, "irena-ff-gen-all": 0.602, "wdi-DT.ODA.ODAT.GN.ZS": 0.308, "ihme-other-unspecified-infectious-diseases": 0.945, "ihme-latent-tuberculosis-infection": 0.834, "ihme-peripheral-artery-disease": 0.036, "ihme-chronic-respiratory-diseases": 0.897}, "categories": {"Acute hepatitis": 0.018, "Public Sector": 0.511, "Profile": 0.888, "Economic Indicators": 0.34}}}