{"wdi2-SE.PRM.TCHR": {"data": {"2014": {"ATG": 714.0, "BHS": 1743.0, "BHR": 8896.0, "BRB": 1665.0, "BLZ": 2321.0, "BMU": 610.0, "VGB": 279.0, "CPV": 2965.0, "CUB": 84209.0, "DMA": 540.0, "DOM": 61659.0, "GRD": 902.0, "JAM": 12055.0, "KIR": 614.0, "MDV": 3292.0, "MUS": 5629.0, "NRU": 40.0, "STP": 1054.0, "SYC": 662.0, "SLB": 5019.0, "KNA": 401.0, "LCA": 1216.0, "VCT": 856.0, "SUR": 5263.0, "TON": 782.0, "TCA": 285.0}, "2020": {"BHR": 9112.0, "BRB": 1476.0, "BLZ": 2598.0, "VGB": 286.0, "CYM": 346.8999939, "CUB": 84629.0, "DMA": 520.0, "DOM": 65041.13672, "JAM": 11292.0, "KIR": 704.0, "FSM": 603.0, "NRU": 63.0, "SYC": 623.0, "LCA": 1077.0, "TON": 779.0, "VUT": 13975.0}, "1995": {"BHS": 1485.0, "BHR": 3536.0, "BMU": 463.0, "VGB": 169.0, "CUB": 74225.0, "FJI": 4992.0, "GRD": 860.0, "GUY": 3417.0, "HTI": 36460.0, "KIR": 624.0, "MUS": 5137.0, "WSM": 1475.0, "SYC": 584.0, "SGP": 10356.0, "KNA": 368.0, "LCA": 1142.0, "TON": 784.0}, "1996": {"COM": 1508.0, "CUB": 90565.0, "FJI": 5021.0, "GRD": 869.0, "GUY": 3345.0, "HTI": 38743.0, "KIR": 732.0, "MUS": 5215.0, "WSM": 1479.0, "STP": 638.0, "SYC": 577.0, "SGP": 10618.0, "LCA": 1180.0, "TON": 804.0, "TTO": 7296.0}, "1997": {"BMU": 478.0, "CUB": 92820.0, "FJI": 5011.0, "GRD": 878.0, "GUY": 3461.0, "HTI": 41160.0, "KIR": 727.0, "MUS": 5200.0, "SYC": 633.0, "SLB": 2850.0, "LCA": 1214.0, "TON": 792.0, "TTO": 7311.0, "TCA": 90.0}, "1998": {"CPV": 3219.0, "CUB": 91310.0, "DOM": 41329.0, "FJI": 5054.0, "GRD": 859.0, "HTI": 44472.0, "KIR": 720.0, "MDV": 2805.0, "MUS": 5065.0, "NRU": 71.0, "SYC": 656.0, "KNA": 320.0, "LCA": 1175.0, "VCT": 1007.0, "TON": 752.0, "VUT": 1190.0}, "1999": {"ABW": 473.0, "BHS": 2406.0, "BRB": 1395.0, "BLZ": 1880.0, "VGB": 153.0, "CPV": 3228.0, "CYM": 209.0, "COM": 2381.0, "CUB": 91220.0, "DMA": 608.0, "DOM": 42184.0, "GRD": 872.0, "GUY": 4022.0, "KIR": 581.0, "MDV": 3051.0, "MHL": 550.0, "MUS": 5107.0, "PLW": 127.0, "WSM": 1137.0, "STP": 660.0, "SYC": 682.0, "SLB": 3014.0, "LCA": 1168.0, "VCT": 1004.0, "TON": 803.0, "TTO": 8074.0, "TCA": 99.0, "TUV": 72.0, "VUT": 1421.0}, "2000": {"ATG": 695.0, "ABW": 486.0, "BRB": 1393.0, "BLZ": 1921.0, "VGB": 164.0, "CPV": 3190.0, "CYM": 237.0, "COM": 2536.0, "CUB": 90920.0, "DMA": 602.0, "DOM": 43941.0, "FJI": 4079.0, "GRD": 796.0, "GNB": 3405.0, "GUY": 4153.0, "KIR": 460.0, "MDV": 3246.0, "MUS": 5178.0, "NRU": 74.0, "PLW": 124.0, "PNG": 15798.0, "WSM": 1167.0, "SYC": 684.0, "KNA": 356.0, "LCA": 1091.0, "VCT": 1032.0, "TON": 754.0, "TTO": 8122.0, "TUV": 77.0, "VUT": 1582.0}, "2001": {"ABW": 498.0, "BRB": 1422.0, "BLZ": 1983.0, "BMU": 536.0, "VGB": 167.0, "CPV": 3214.0, "CYM": 234.0, "CUB": 93758.0, "DMA": 617.0, "FJI": 4125.0, "GRD": 765.0, "GUY": 4202.0, "KIR": 664.0, "MDV": 3155.0, "MUS": 5379.0, "NRU": 64.0, "PNG": 14390.0, "WSM": 1166.0, "SYC": 712.0, "KNA": 355.0, "LCA": 1052.0, "VCT": 1004.0, "SUR": 3253.0, "TLS": 2991.0, "TON": 823.0, "TTO": 7866.0, "TCA": 123.0, "TUV": 78.0, "VUT": 1537.0}, "2002": {"ABW": 516.0, "BHS": 2029.0, "BRB": 1471.0, "BMU": 548.0, "VGB": 168.0, "CPV": 3121.0, "CYM": 240.0, "COM": 2660.0, "DMA": 589.0, "DOM": 42929.0, "FJI": 4107.0, "KIR": 660.0, "MDV": 3411.0, "MHL": 517.0, "MUS": 5256.0, "NRU": 61.0, "WSM": 1121.0, "STP": 881.0, "SYC": 693.0, "KNA": 386.0, "LCA": 1091.0, "VCT": 1049.0, "SUR": 3291.0, "TLS": 3901.0, "TON": 773.0, "TTO": 7210.0, "TCA": 119.0, "TUV": 77.0, "VUT": 1614.0}, "2003": {"ABW": 537.0, "BRB": 1460.0, "BLZ": 2274.0, "BMU": 548.0, "VGB": 201.0, "CPV": 3145.0, "COM": 2908.0, "CUB": 86641.0, "DMA": 550.0, "FJI": 4028.0, "GRD": 888.0, "GUY": 4174.0, "JAM": 10968.0, "KIR": 596.0, "MDV": 3644.0, "MUS": 5620.0, "NRU": 63.0, "SYC": 675.0, "KNA": 368.0, "LCA": 1103.0, "VCT": 1061.0, "TLS": 3926.0, "TON": 824.0, "TTO": 7623.0, "TCA": 119.0, "TUV": 75.0, "VUT": 1814.0}, "2004": {"ABW": 552.0, "BHS": 2150.0, "BRB": 1416.0, "BLZ": 2109.0, "BMU": 560.0, "VGB": 203.0, "CPV": 3169.0, "CYM": 251.0, "COM": 2967.0, "CUB": 88498.0, "DMA": 519.0, "DOM": 50791.0, "FJI": 4029.0, "GRD": 895.0, "JAM": 12032.0, "KIR": 633.0, "MDV": 2786.0, "MUS": 5741.0, "NRU": 58.0, "STP": 929.0, "SYC": 659.0, "KNA": 367.0, "LCA": 1050.0, "VCT": 1018.0, "TLS": 3618.0, "TON": 843.0, "TTO": 7839.0, "TUV": 73.0, "VUT": 1947.0}, "2005": {"ABW": 567.0, "BRB": 1469.0, "BLZ": 2127.0, "BMU": 571.0, "VGB": 194.0, "CPV": 3190.0, "CYM": 253.0, "CUB": 86827.0, "DMA": 519.0, "DOM": 53015.0, "GRD": 791.0, "GUY": 4164.0, "KIR": 654.0, "MDV": 2882.0, "MUS": 5531.0, "NRU": 65.0, "STP": 990.0, "SYC": 671.0, "KNA": 360.0, "LCA": 1073.0, "SUR": 3520.0, "TON": 839.0, "TTO": 7839.0}, "2006": {"ABW": 572.0, "BHS": 2335.0, "BLZ": 2245.0, "BMU": 567.0, "VGB": 194.0, "CPV": 3210.0, "CYM": 286.0, "CUB": 89181.0, "DMA": 517.0, "DOM": 54838.0, "GNB": 4327.0, "KIR": 606.0, "MDV": 3336.0, "MUS": 5598.0, "NRU": 52.0, "SYC": 692.0, "LCA": 1022.0, "SUR": 4136.0, "TON": 760.0}, "2007": {"ATG": 538.0, "ABW": 594.0, "BHS": 2420.0, "BRB": 1553.0, "BLZ": 2268.0, "VGB": 215.0, "CPV": 3170.0, "CYM": 335.0, "CUB": 91530.0, "DMA": 499.0, "DOM": 56744.0, "GRD": 871.0, "GUY": 4173.0, "KIR": 639.0, "MDV": 3463.0, "MUS": 5548.0, "NRU": 62.0, "WSM": 920.0, "SYC": 711.0, "SGP": 14242.0, "KNA": 372.0, "LCA": 969.0, "VCT": 933.0, "SUR": 4913.0, "TON": 665.0, "TTO": 8171.0, "VUT": 1592.0}, "2008": {"ATG": 675.0, "ABW": 579.0, "BHS": 2333.0, "BRB": 1698.0, "BLZ": 2299.0, "CPV": 3132.0, "CYM": 309.0, "COM": 3685.0, "CUB": 90677.0, "DMA": 500.0, "DOM": 66539.0, "FJI": 3939.0, "GRD": 615.0, "GUY": 4204.0, "KIR": 645.0, "MDV": 3551.0, "MUS": 5495.0, "NRU": 56.0, "SYC": 670.0, "SGP": 14850.0, "KNA": 401.0, "LCA": 978.0, "VCT": 916.0, "SUR": 4354.0, "TON": 665.0, "TTO": 7628.0}, "2009": {"ATG": 695.0, "ABW": 582.0, "BHS": 2683.0, "BRB": 1607.0, "BLZ": 2325.0, "VGB": 232.0, "CPV": 3072.0, "CUB": 92016.0, "DMA": 510.0, "DOM": 52937.0, "GRD": 830.0, "GUY": 3942.0, "MDV": 3524.0, "MUS": 5454.0, "WSM": 936.0, "STP": 1291.0, "SYC": 624.0, "SGP": 16171.0, "KNA": 443.0, "LCA": 1011.0, "VCT": 879.0, "SUR": 4620.0, "TLS": 7331.0, "TON": 680.0, "TTO": 7447.0}, "2010": {"ATG": 747.0, "ABW": 586.0, "BHS": 2402.0, "BRB": 1742.0, "BLZ": 2367.0, "BMU": 608.0, "VGB": 242.0, "CPV": 3009.0, "CUB": 93414.0, "DMA": 508.0, "DOM": 51615.0, "GRD": 851.0, "GNB": 5371.0, "GUY": 4031.0, "MDV": 3602.0, "MUS": 5472.0, "WSM": 1021.0, "SYC": 691.0, "SLB": 4789.0, "KNA": 443.0, "LCA": 1051.0, "VCT": 887.0, "SUR": 4749.0, "TLS": 7622.0, "TON": 677.0, "VUT": 1931.0}, "2011": {"ATG": 748.0, "ABW": 604.0, "BHS": 1996.0, "BHR": 7679.0, "BRB": 1720.0, "BLZ": 2391.0, "BMU": 486.0, "VGB": 263.0, "CPV": 2972.0, "CYM": 330.0, "COM": 4201.0, "CUB": 90918.0, "DMA": 511.0, "DOM": 51464.0, "FJI": 3296.0, "GUY": 4012.0, "JAM": 12380.0, "MDV": 3275.0, "MUS": 5701.0, "STP": 1183.0, "SYC": 656.0, "SLB": 5022.0, "KNA": 459.0, "LCA": 1071.0, "SUR": 4880.0, "TLS": 7714.0, "TON": 706.0}, "2012": {"ATG": 755.0, "ABW": 601.0, "BHS": 1634.0, "BHR": 8117.0, "BLZ": 2486.0, "BMU": 429.0, "CPV": 2956.0, "CYM": 303.0, "CUB": 88699.0, "DMA": 516.0, "DOM": 54322.0, "FJI": 3671.0, "GUY": 4079.0, "JAM": 12409.0, "MDV": 3405.0, "MUS": 5427.0, "STP": 1183.0, "SYC": 693.0, "SXM": 318.0, "SLB": 5097.0, "KNA": 385.0, "LCA": 1054.0, "VCT": 877.0, "SUR": 5019.0, "TON": 816.0}, "2013": {"BHS": 1803.0, "BHR": 8413.0, "BLZ": 2329.0, "BMU": 573.0, "CPV": 2955.0, "CYM": 303.0, "COM": 4322.0, "CUB": 85202.0, "DMA": 529.0, "DOM": 54959.0, "GRD": 875.0, "JAM": 12842.0, "MDV": 3411.0, "MUS": 5512.0, "STP": 1107.0, "SYC": 661.0, "SLB": 4880.0, "KNA": 385.0, "LCA": 1065.0, "VCT": 890.0, "SUR": 5114.0, "TON": 670.0, "VUT": 1936.0}, "2015": {"ATG": 703.0, "BHS": 1555.0, "BHR": 9219.0, "BRB": 1560.0, "BLZ": 2548.0, "BMU": 398.0, "VGB": 286.0, "CPV": 2988.0, "CUB": 83798.0, "DMA": 538.0, "DOM": 71463.0, "GRD": 791.0, "JAM": 11806.0, "MDV": 4075.0, "MUS": 5400.0, "FSM": 698.0, "STP": 917.0, "SYC": 654.0, "SLB": 4051.0, "KNA": 362.0, "LCA": 1088.0, "VCT": 897.0, "SUR": 5395.0, "TON": 785.0, "TUV": 117.0, "VUT": 1729.0}, "2016": {"BHS": 1611.0, "BHR": 9303.0, "BRB": 1553.0, "BLZ": 2552.0, "BMU": 420.0, "VGB": 314.0, "CPV": 2995.0, "CUB": 84101.0, "DMA": 560.0, "DOM": 69495.0, "GRD": 854.0, "JAM": 11180.0, "KIR": 656.0, "MDV": 4252.0, "MUS": 5468.0, "FSM": 612.0, "NRU": 45.0, "PNG": 35896.0, "STP": 1132.0, "SYC": 644.0, "SGP": 15734.0, "SLB": 4262.0, "KNA": 393.0, "LCA": 1087.0, "VCT": 908.0, "SUR": 5367.0, "TUV": 77.0}, "2017": {"ATG": 825.0, "BHS": 1555.0, "BHR": 9332.0, "BRB": 1446.0, "BLZ": 2630.0, "VGB": 287.0, "CPV": 3016.0, "COM": 6429.0, "CUB": 83125.0, "DOM": 66255.0, "GRD": 832.0, "JAM": 11172.0, "KIR": 655.0, "MDV": 4460.0, "MUS": 5184.0, "STP": 1193.0, "SYC": 644.0, "SGP": 15969.0, "SLB": 4205.0, "LCA": 1054.0, "VCT": 905.0, "SUR": 5309.0, "TLS": 8057.724121}, "2018": {"ATG": 816.0, "BHS": 1517.0, "BHR": 9551.0, "BRB": 1445.0, "BLZ": 2566.0, "VGB": 247.0, "CPV": 3043.0, "CYM": 273.0, "COM": 4428.0, "CUB": 80922.0, "DOM": 64810.0, "GRD": 807.0, "JAM": 10036.0, "MDV": 4582.0, "MUS": 5534.0, "SYC": 639.0, "SGP": 16294.0, "SLB": 4149.0, "LCA": 1077.0, "VCT": 917.0, "SUR": 5054.0, "TLS": 7898.257813, "TON": 781.0, "TCA": 208.0, "TUV": 85.0}, "2019": {"BHR": 9460.0, "BRB": 1398.0, "BLZ": 2623.0, "VGB": 268.0, "CPV": 3093.0, "CUB": 80503.0, "DMA": 525.0, "DOM": 65556.11719, "FJI": 6211.0, "JAM": 11347.0, "MDV": 5084.0, "MUS": 5639.0, "FSM": 612.0, "NRU": 69.0, "SYC": 636.0, "SGP": 16545.0, "SLB": 4348.0, "LCA": 1081.0, "SUR": 5257.0, "TLS": 7749.491211, "TON": 812.0, "TUV": 106.0, "VUT": 1928.0}, "2021": {"MUS": 5903.0}, "1990": {"BHR": 3059.0, "BRB": 1602.0, "VGB": 123.0, "CPV": 2028.0, "COM": 1900.0, "CUB": 71887.0, "GRD": 763.0, "JAM": 10076.0, "KIR": 514.0, "MUS": 6507.0, "PNG": 13105.0, "STP": 559.0, "SGP": 10006.0, "SLB": 2457.0, "KNA": 346.0, "LCA": 1137.0, "SUR": 2733.0, "TON": 689.0}, "1991": {"BHR": 3092.0, "VGB": 126.0, "CPV": 1896.0, "COM": 1995.0, "CUB": 70962.0, "DMA": 439.0, "GUY": 3509.0, "KIR": 533.0, "MUS": 6369.0, "PNG": 13417.0, "SGP": 9843.0, "SLB": 2388.0, "KNA": 363.0, "LCA": 1127.0, "VCT": 1119.0, "SUR": 2686.0, "TON": 714.0, "TTO": 7473.0, "VUT": 869.0}, "1992": {"BHR": 3085.0, "BRB": 1553.0, "VGB": 151.0, "COM": 1894.0, "CUB": 74354.0, "DMA": 414.0, "FJI": 4644.0, "GRD": 799.0, "GUY": 3657.0, "HTI": 25605.0, "KIR": 545.0, "MUS": 6272.0, "PNG": 14117.0, "SGP": 10188.0, "SLB": 2490.0, "KNA": 350.0, "LCA": 1181.0, "SUR": 2982.0, "TON": 784.0, "TTO": 7512.0, "VUT": 852.0}, "1993": {"BHR": 3312.0, "COM": 1771.0, "CUB": 76161.0, "GRD": 831.0, "GUY": 3669.0, "HTI": 32285.0, "KIR": 537.0, "MUS": 5931.0, "PNG": 14378.0, "SYC": 548.0, "SGP": 10711.0, "SLB": 2357.0, "LCA": 1204.0, "SUR": 3695.0, "TON": 754.0, "TTO": 7647.0}, "1994": {"BHS": 1581.0, "BHR": 3386.0, "VGB": 166.0, "CPV": 2657.0, "COM": 1737.0, "CUB": 76193.0, "FJI": 4921.0, "GRD": 856.0, "GUY": 3453.0, "HTI": 34310.0, "KIR": 542.0, "MUS": 5483.0, "PNG": 15298.0, "SYC": 588.0, "SGP": 10553.0, "SLB": 2514.0, "KNA": 378.0, "LCA": 1174.0, "VCT": 1053.0, "TON": 701.0, "TTO": 7210.0, "TUV": 69.0}, "1970": {"MUS": 4731.0, "PNG": 6439.0, "WSM": 1051.0, "SYC": 381.0, "SGP": 12259.0, "SLB": 885.0, "TON": 658.0, "VUT": 778.0}, "1971": {"BHS": 707.0, "BMU": 341.0, "VGB": 94.0, "CPV": 730.0, "COM": 361.0, "CUB": 56555.0, "DOM": 13796.0, "GRD": 800.0, "GNB": 616.0, "GUY": 4485.0, "HTI": 7833.0, "JAM": 8053.0, "MUS": 4815.0, "FSM": 1267.0, "NRU": 65.0, "PNG": 6738.0, "WSM": 937.0, "STP": 271.0, "SYC": 393.0, "SGP": 11965.0, "SLB": 1060.0, "SUR": 2487.0, "TON": 648.0, "TTO": 6548.0, "TCA": 106.0, "VUT": 782.0}, "1972": {"ATG": 472.0, "BHS": 751.0, "BMU": 363.0, "VGB": 94.0, "CPV": 973.0, "COM": 396.0, "CUB": 57110.0, "DOM": 14782.0, "GRD": 884.0, "GNB": 630.0, "HTI": 7472.0, "JAM": 9471.0, "KIR": 531.0, "MUS": 4952.0, "PNG": 7381.0, "WSM": 1137.0, "STP": 301.0, "SYC": 409.0, "SGP": 10858.0, "SLB": 1088.0, "LCA": 888.0, "VCT": 1765.0, "SUR": 2729.0, "TON": 642.0, "TTO": 6741.0, "TCA": 90.0, "VUT": 790.0}, "1973": {"BHR": 1900.0, "BMU": 354.0, "VGB": 94.0, "COM": 533.0, "CUB": 60132.0, "DMA": 504.0, "DOM": 15216.0, "GRD": 816.0, "HTI": 8074.0, "KIR": 371.0, "MUS": 5278.0, "PNG": 7438.0, "WSM": 1011.0, "SYC": 421.0, "SGP": 11135.0, "SLB": 1088.0, "LCA": 829.0, "SUR": 2870.0, "TON": 641.0, "TTO": 6704.0, "VUT": 731.0}, "1974": {"ATG": 440.0, "BHR": 1723.0, "BMU": 346.0, "CPV": 1068.0, "COM": 554.0, "CUB": 67891.0, "DMA": 448.0, "DOM": 15821.0, "GRD": 764.0, "GUY": 4077.0, "HTI": 10265.0, "MUS": 5568.0, "PNG": 7545.0, "SYC": 416.0, "SGP": 10985.0, "SLB": 974.0, "LCA": 892.0, "SUR": 3089.0, "TON": 668.0, "TTO": 6701.0, "VUT": 814.0}, "1975": {"ATG": 460.0, "BHS": 1187.0, "BHR": 1916.0, "BMU": 325.0, "VGB": 100.0, "CPV": 1242.0, "CUB": 74237.0, "DMA": 466.0, "DOM": 16824.0, "HTI": 11320.0, "JAM": 9417.0, "KIR": 449.0, "MUS": 5791.0, "PNG": 7544.0, "WSM": 1216.0, "SYC": 428.0, "SGP": 10777.0, "SLB": 1071.0, "LCA": 919.0, "SUR": 3005.0, "TON": 688.0, "TTO": 6566.0, "TCA": 94.0}, "1976": {"ATG": 524.0, "BHS": 1294.0, "BHR": 2044.0, "VGB": 113.0, "CPV": 1243.0, "COM": 756.0, "CUB": 77472.0, "DOM": 17932.0, "GNB": 2163.0, "GUY": 4052.0, "HTI": 11816.0, "KIR": 418.0, "MUS": 5848.0, "PNG": 8067.0, "WSM": 1322.0, "STP": 422.0, "SYC": 435.0, "SGP": 10597.0, "SLB": 1060.0, "LCA": 953.0, "VCT": 1210.0, "SUR": 2552.0, "TON": 767.0, "TTO": 6471.0, "TCA": 83.0}, "1977": {"ATG": 419.0, "BHS": 1417.0, "BHR": 2010.0, "BMU": 374.0, "CPV": 1314.0, "CYM": 88.0, "CUB": 80845.0, "DMA": 462.0, "GRD": 633.0, "GUY": 4335.0, "HTI": 12953.0, "JAM": 9889.0, "KIR": 435.0, "MUS": 6088.0, "PNG": 8568.0, "WSM": 1346.0, "SGP": 10345.0, "SLB": 1069.0, "LCA": 947.0, "SUR": 3016.0, "TTO": 6474.0, "TCA": 83.0, "VUT": 839.0}, "1978": {"ATG": 414.0, "BHR": 2235.0, "BRB": 1227.0, "BMU": 319.0, "CPV": 1412.0, "CUB": 86253.0, "GRD": 610.0, "GUY": 4460.0, "HTI": 12554.0, "KIR": 429.0, "MUS": 6352.0, "PNG": 8590.0, "WSM": 1471.0, "STP": 527.0, "SYC": 427.0, "SGP": 10347.0, "SLB": 1010.0, "LCA": 953.0, "SUR": 3077.0, "TON": 761.0, "TTO": 6363.0, "TCA": 80.0, "VUT": 991.0}, "1979": {"ATG": 390.0, "BHR": 2345.0, "BRB": 1261.0, "BMU": 262.0, "VGB": 98.0, "CPV": 1552.0, "CUB": 86738.0, "GRD": 608.0, "GNB": 2878.0, "GUY": 4215.0, "HTI": 12751.0, "JAM": 8453.0, "KIR": 429.0, "MUS": 6567.0, "PNG": 9312.0, "WSM": 1458.0, "SYC": 405.0, "SGP": 10492.0, "SLB": 1065.0, "LCA": 999.0, "SUR": 3068.0, "TON": 818.0, "TTO": 6130.0}, "1980": {"BHS": 1218.0, "BHR": 2479.0, "BMU": 262.0, "CPV": 1396.0, "CYM": 112.0, "CUB": 86519.0, "GRD": 587.0, "GNB": 3102.0, "GUY": 4003.0, "HTI": 13472.0, "JAM": 8783.0, "KIR": 435.0, "MUS": 6379.0, "WSM": 1438.0, "STP": 577.0, "SGP": 9463.0, "SLB": 1148.0, "KNA": 331.0, "LCA": 942.0, "SUR": 3476.0, "TON": 781.0, "TTO": 6443.0, "VUT": 986.0}, "1981": {"BHS": 1261.0, "BHR": 2577.0, "BMU": 312.0, "VGB": 109.0, "CPV": 1436.0, "COM": 1292.0, "CUB": 84041.0, "FJI": 4150.0, "GRD": 776.0, "GNB": 3257.0, "GUY": 3909.0, "HTI": 14581.0, "JAM": 8676.0, "KIR": 447.0, "MUS": 6638.0, "PNG": 9935.0, "WSM": 1288.0, "STP": 588.0, "SGP": 9505.0, "SLB": 1171.0, "LCA": 957.0, "SUR": 2803.0, "TON": 695.0, "TTO": 7002.0, "VUT": 1076.0}, "1982": {"BHS": 1151.0, "BHR": 2543.0, "BMU": 326.0, "CUB": 83113.0, "GRD": 760.0, "GNB": 3315.0, "GUY": 3493.0, "HTI": 14927.0, "KIR": 450.0, "MUS": 6623.0, "PNG": 10163.0, "WSM": 1460.0, "STP": 617.0, "SGP": 10286.0, "SLB": 1199.0, "LCA": 1012.0, "VCT": 1184.0, "SUR": 2793.0, "TON": 793.0, "TTO": 7298.0}, "1983": {"BHS": 1555.0, "BHR": 2736.0, "BRB": 1492.0, "BMU": 322.0, "VGB": 121.0, "COM": 1617.0, "CUB": 83358.0, "DOM": 23578.0, "GRD": 764.0, "GNB": 3363.0, "GUY": 3489.0, "HTI": 16986.0, "JAM": 10699.0, "KIR": 453.0, "MUS": 6572.0, "WSM": 1502.0, "STP": 628.0, "SGP": 9921.0, "SLB": 1390.0, "LCA": 985.0, "SUR": 2966.0, "TON": 832.0, "TTO": 7522.0, "VUT": 934.0}, "1984": {"BHS": 1565.0, "BHR": 2910.0, "BRB": 1317.0, "BMU": 316.0, "VGB": 117.0, "CPV": 1445.0, "COM": 1607.0, "CUB": 83424.0, "GRD": 775.0, "GNB": 3303.0, "GUY": 3257.0, "HTI": 18483.0, "JAM": 10358.0, "KIR": 471.0, "MUS": 6465.0, "PNG": 11184.0, "STP": 538.0, "SGP": 10657.0, "SLB": 1536.0, "KNA": 357.0, "LCA": 1084.0, "SUR": 2971.0, "TON": 810.0, "TTO": 7346.0}, "1985": {"BHS": 1561.0, "BHR": 2892.0, "BRB": 1421.0, "BMU": 309.0, "COM": 1997.0, "CUB": 79610.0, "DOM": 27751.0, "GRD": 756.0, "GNB": 3085.0, "GUY": 3284.0, "HTI": 20311.0, "JAM": 10051.0, "KIR": 460.0, "MUS": 6450.0, "NRU": 71.0, "STP": 517.0, "SGP": 10363.0, "SLB": 1496.0, "KNA": 339.0, "LCA": 1107.0, "SUR": 2809.0, "TON": 744.0, "TTO": 7593.0}, "1986": {"BHS": 1767.0, "BHR": 2856.0, "CPV": 1493.0, "COM": 1901.0, "CUB": 77111.0, "HTI": 23200.0, "JAM": 9648.0, "KIR": 467.0, "MUS": 6371.0, "PNG": 12318.0, "WSM": 1511.0, "SGP": 10264.0, "SLB": 1849.0, "KNA": 353.0, "LCA": 1084.0, "SUR": 3010.0, "TON": 758.0, "TTO": 7627.0}, "1987": {"BHR": 2906.0, "CPV": 1791.0, "COM": 1808.0, "CUB": 75273.0, "GRD": 821.0, "GNB": 3121.0, "HTI": 21102.0, "JAM": 9467.0, "KIR": 455.0, "MUS": 6504.0, "PNG": 12294.0, "STP": 574.0, "SGP": 10199.0, "KNA": 266.0, "LCA": 1103.0, "VCT": 1258.0, "SUR": 2705.0, "TON": 772.0, "TTO": 7685.0}, "1988": {"BHR": 2887.0, "CPV": 1892.0, "COM": 1777.0, "CUB": 73874.0, "GRD": 806.0, "GNB": 3065.0, "JAM": 9888.0, "KIR": 459.0, "MUS": 6404.0, "PNG": 12527.0, "STP": 616.0, "SGP": 9962.0, "KNA": 263.0, "LCA": 1066.0, "SUR": 2680.0, "TTO": 7686.0}, "1989": {"BHR": 2882.0, "BRB": 1609.0, "CPV": 1981.0, "COM": 1764.0, "CUB": 73216.0, "JAM": 10251.0, "KIR": 507.0, "MUS": 6324.0, "PNG": 13171.0, "SGP": 9998.0, "KNA": 331.0, "LCA": 1082.0, "SUR": 2921.0, "TTO": 7545.0, "VUT": 970.0}, "recentValue": {"ATG": "2018", "ABW": "2012", "BHS": "2018", "BMU": "2016", "BHR": "2020", "BRB": "2020", "BLZ": "2020", "VGB": "2020", "CPV": "2019", "CYM": "2020", "COM": "2018", "CUB": "2020", "DMA": "2020", "DOM": "2020", "FJI": "2019", "GRD": "2018", "GNB": "2010", "GUY": "2012", "HTI": "1998", "JAM": "2020", "KIR": "2020", "MDV": "2019", "MHL": "2002", "MUS": "2021", "FSM": "2020", "NRU": "2020", "PLW": "2000", "PNG": "2016", "WSM": "2010", "STP": "2017", "SYC": "2020", "SGP": "2019", "SXM": "2012", "SLB": "2019", "KNA": "2016", "VCT": "2018", "LCA": "2020", "SUR": "2019", "TLS": "2019", "TTO": "2009", "TON": "2020", "TUV": "2019", "TCA": "2018", "VUT": "2020"}, "recentYear": {"ATG": "2018", "ABW": "2012", "BHS": "2018", "BMU": "2016", "BHR": "2020", "BRB": "2020", "BLZ": "2020", "VGB": "2020", "CPV": "2019", "CYM": "2020", "COM": "2018", "CUB": "2020", "DMA": "2020", "DOM": "2020", "FJI": "2019", "GRD": "2018", "GNB": "2010", "GUY": "2012", "HTI": "1998", "JAM": "2020", "KIR": "2020", "MDV": "2019", "MHL": "2002", "MUS": "2021", "FSM": "2020", "NRU": "2020", "PLW": "2000", "PNG": "2016", "WSM": "2010", "STP": "2017", "SYC": "2020", "SGP": "2019", "SXM": "2012", "SLB": "2019", "KNA": "2016", "VCT": "2018", "LCA": "2020", "SUR": "2019", "TLS": "2019", "TTO": "2009", "TON": "2020", "TUV": "2019", "TCA": "2018", "VUT": "2020"}}, "def": "Primary education teachers includes full-time and part-time teachers.", "name": "Primary education", "source": "UNESCO Institute for Statistics (http://uis.unesco.org/). Data as of September 2020.", "dataset": "UNESCO Institute for Statistics (http://uis.unesco.org/). Data as of September 2020.", "category": "Education", "subcategory": "Inputs", "link": "https://data.worldbank.org/indicator/wdi2-SE.PRM.TCHR", "dim": "teachers", "priority": "1.0", "units": "teachers"}, "confidenceIntervals": {"2014": {"BHS": 435.75, "BHR": 1270.857142857143, "CPV": 741.25, "SLB": 501.9, "LCA": 1216.0, "VCT": 856.0, "TON": 78.2}, "2020": {"FSM": 150.75, "SYC": 623.0}, "1995": {"BHR": 3536.0, "GUY": 3417.0, "KIR": 62.4, "LCA": 163.14285714285714}, "1996": {"COM": 215.42857142857142, "CUB": 12937.857142857143, "GRD": 217.25, "WSM": 147.9, "STP": 91.14285714285714, "TTO": 1042.2857142857142}, "1997": {"BMU": 478.0, "SYC": 158.25, "SLB": 407.14285714285717}, "1998": {"CUB": 91310.0, "HTI": 11118.0, "MDV": 2805.0, "NRU": 71.0, "SYC": 93.71428571428571}, "1999": {"CUB": 9122.0, "KIR": 581.0, "WSM": 113.7, "VCT": 251.0}, "2000": {"ATG": 99.28571428571429, "BLZ": 1921.0, "CPV": 797.5, "CUB": 90920.0, "DOM": 43941.0, "GRD": 113.71428571428571, "MUS": 5178.0, "PLW": 12.4, "SYC": 97.71428571428571, "TTO": 812.2, "TUV": 7.7}, "2001": {"DMA": 88.14285714285714, "FJI": 1031.25, "GUY": 420.2, "KIR": 66.4}, "2002": {"CPV": 3121.0, "COM": 380.0, "DOM": 42929.0, "MDV": 487.2857142857143, "TLS": 390.1, "TTO": 721.0, "TCA": 29.75, "VUT": 230.57142857142858}, "2003": {"BLZ": 324.85714285714283, "DMA": 55.0, "GUY": 596.2857142857143, "NRU": 15.75, "SYC": 67.5, "TLS": 981.5, "TON": 206.0, "VUT": 1814.0}, "2004": {"ABW": 55.2, "CYM": 35.857142857142854, "COM": 296.7, "DMA": 51.9, "STP": 232.25}, "2005": {"CYM": 36.142857142857146, "GRD": 79.1, "NRU": 6.5, "SYC": 67.1}, "2006": {"CPV": 3210.0, "DMA": 129.25, "DOM": 5483.8}, "2007": {"ATG": 53.8, "ABW": 148.5, "VGB": 21.5, "DMA": 49.9, "DOM": 8106.285714285715, "GUY": 596.1428571428571, "MDV": 346.3, "LCA": 138.42857142857142, "TTO": 817.1}, "2008": {"COM": 368.5, "GUY": 1051.0, "NRU": 14.0, "LCA": 97.8}, "2009": {"BHS": 383.2857142857143, "VGB": 232.0, "DOM": 5293.7, "MUS": 779.1428571428571, "STP": 1291.0, "SYC": 156.0}, "2010": {"DMA": 72.57142857142857}, "2011": {"BHS": 199.6, "BLZ": 239.1, "CYM": 330.0, "DOM": 51464.0, "JAM": 1238.0, "MDV": 327.5, "MUS": 814.4285714285714, "TLS": 7714.0, "TON": 100.85714285714286}, "2012": {"ATG": 107.85714285714286, "ABW": 601.0, "BHR": 2029.25, "BLZ": 355.14285714285717, "BMU": 42.9, "CPV": 2956.0, "FJI": 917.75, "STP": 118.3, "SYC": 173.25, "SLB": 509.7}, "2013": {"CYM": 43.285714285714285, "COM": 4322.0, "CUB": 21300.5, "DOM": 7851.285714285715, "JAM": 1284.2, "SYC": 66.1, "SLB": 697.1428571428571, "KNA": 55.0}, "2015": {"ATG": 703.0, "BLZ": 637.0, "CPV": 2988.0, "FSM": 69.8, "TUV": 117.0}, "2016": {"BHS": 1611.0, "BRB": 221.85714285714286, "BMU": 420.0, "VGB": 31.4, "CUB": 8410.1, "DMA": 56.0, "DOM": 17373.75, "PNG": 5128.0, "TUV": 77.0}, "2017": {"ATG": 82.5, "BHR": 1333.142857142857, "CPV": 754.0, "DOM": 16563.75, "MDV": 637.1428571428571, "STP": 298.25, "SYC": 64.4}, "2018": {"BRB": 361.25, "CYM": 27.3, "COM": 1107.0, "DOM": 6481.0, "SYC": 91.28571428571429, "SGP": 16294.0, "VCT": 131.0, "TLS": 1974.56445325}, "2019": {"BRB": 199.71428571428572, "CPV": 773.25, "DOM": 65556.11719, "FJI": 887.2857142857143, "MDV": 1271.0, "LCA": 108.1, "TON": 116.0}, "2021": {}, "1990": {"CPV": 289.7142857142857, "COM": 271.42857142857144, "CUB": 10269.57142857143, "MUS": 1626.75, "STP": 55.9, "SGP": 10006.0, "LCA": 113.7, "SUR": 683.25}, "1991": {"BHR": 773.0, "CPV": 270.85714285714283, "PNG": 1916.7142857142858, "LCA": 281.75, "TTO": 7473.0, "VUT": 124.14285714285714}, "1992": {"COM": 270.57142857142856, "GUY": 365.7, "HTI": 25605.0, "KIR": 54.5, "SLB": 622.5, "TTO": 1878.0, "VUT": 213.0}, "1993": {"COM": 1771.0, "HTI": 4612.142857142857, "KIR": 76.71428571428571, "MUS": 847.2857142857143, "SGP": 1530.142857142857}, "1994": {"BHS": 1581.0, "COM": 434.25, "GUY": 863.25, "HTI": 8577.5, "PNG": 15298.0}, "1970": {"WSM": 1051.0, "SYC": 54.42857142857143}, "1971": {"BHS": 176.75, "VGB": 9.4, "GRD": 80.0, "HTI": 783.3, "SLB": 151.42857142857142, "VUT": 195.5}, "1972": {"ATG": 67.42857142857143, "BMU": 51.857142857142854, "VGB": 23.5, "COM": 396.0, "CUB": 8158.571428571428, "DOM": 3695.5, "GRD": 88.4, "SYC": 409.0, "SUR": 389.85714285714283, "TCA": 12.857142857142858}, "1973": {"VGB": 9.4, "CUB": 8590.285714285714, "KIR": 371.0, "PNG": 7438.0, "SGP": 2783.75, "SLB": 1088.0, "LCA": 207.25, "SUR": 2870.0}, "1974": {"COM": 55.4, "DOM": 3955.25, "GUY": 4077.0, "HTI": 10265.0, "PNG": 1886.25, "TON": 167.0, "VUT": 814.0}, "1975": {"BHS": 118.7, "SLB": 153.0}, "1976": {"BHS": 1294.0, "HTI": 11816.0, "TCA": 20.75}, "1977": {"BHS": 1417.0, "DMA": 66.0, "JAM": 988.9, "SGP": 10345.0, "SLB": 106.9}, "1978": {"LCA": 238.25}, "1979": {"BHR": 586.25, "VGB": 9.8, "CPV": 221.71428571428572, "GUY": 1053.75, "WSM": 364.5, "SGP": 1049.2, "SLB": 152.14285714285714, "LCA": 142.71428571428572, "SUR": 3068.0, "TTO": 875.7142857142857}, "1980": {"BMU": 37.42857142857143, "CYM": 11.2, "GRD": 587.0, "GNB": 443.14285714285717, "KIR": 435.0, "WSM": 1438.0, "STP": 57.7, "SLB": 287.0, "TTO": 1610.75}, "1981": {"CPV": 205.14285714285714, "GRD": 776.0, "PNG": 993.5, "SLB": 1171.0, "SUR": 2803.0, "TTO": 700.2}, "1982": {"MUS": 1655.75, "STP": 88.14285714285714, "SGP": 1028.6}, "1983": {"CUB": 11908.285714285714, "GRD": 191.0, "GUY": 348.9, "MUS": 657.2, "STP": 157.0, "SLB": 1390.0, "LCA": 246.25, "TON": 832.0, "TTO": 752.2}, "1984": {"BHS": 223.57142857142858, "GNB": 330.3, "JAM": 10358.0, "MUS": 923.5714285714286, "STP": 134.5, "SUR": 297.1, "TTO": 7346.0}, "1985": {"COM": 199.7, "DOM": 2775.1, "GRD": 756.0, "GNB": 308.5, "JAM": 2512.75, "SGP": 2590.75, "SUR": 702.25, "TON": 106.28571428571429}, "1986": {"BHR": 408.0, "COM": 1901.0}, "1987": {"CUB": 75273.0, "GNB": 3121.0, "JAM": 946.7, "KIR": 65.0, "MUS": 6504.0, "SGP": 2549.75}, "1988": {"CPV": 1892.0, "CUB": 10553.42857142857, "JAM": 9888.0, "KIR": 65.57142857142857, "PNG": 12527.0}, "1989": {"JAM": 1464.4285714285713, "VUT": 970.0}, "recentValue": {"BMU": 288.0, "DOM": 2020.0, "GNB": 287.14285714285717, "MUS": 505.25, "NRU": 288.57142857142856, "KNA": 2016.0, "VCT": 2018.0, "TCA": 288.2857142857143}}, "featureImportances": {"indicators": {"ihme-testicular-cancer": 0.655, "wdi2-per_lm_alllm.cov_q4_tot": 0.615, "paris-98": 0.432, "wdi-BM.GSR.ROYL.CD": 0.92, "oecd-RD_333SALIN": 0.064, "ldc-AFF-Value": 0.183, "ndgain-nd-readiness-social": 0.449, "wdi2-NV.SRV.TOTL.KD.ZG": 0.088, "wdi2-NY.GDP.MINR.RT.ZS": 0.758, "ndgain-id_wate_01-score": 0.027}, "categories": {"Hemoglobinopathies and hemolytic anemias": 0.206, "Blindness and vision loss": 0.194, "Climate": 0.435, "Infrastructure": 0.937}}}