{"unicef-e3": {"data": {"recentValue": {}, "recentYear": {}}, "def": "Number of children of official primary school age who are not enrolled in pre-primary, primary or secondary school, expressed as a percentage of the population of official primary school age.", "name": "Out-of-school rate", "source": "UNESCO Institute for Statistics (UIS). Last update: March 2016", "dataset": "UNESCO Institute for Statistics (UIS). Last update: March 2016", "category": "Education", "subcategory": "None", "link": "https://www.unicef.org/reports/state-worlds-children-2021", "dim": "Primary education, male", "priority": "1.0", "units": "%"}, "confidenceIntervals": {"recentValue": {}}, "featureImportances": {"indicators": {"wdi2-SP.DYN.CDRT.IN": 0.932, "wdi2-SE.PRM.CMPT.ZS": 0.776, "ihme-myocarditis": 0.634, "wdi2-SL.EMP.VULN.MA.ZS": 0.026, "wdi2-TM.TAX.TCOM.WM.AR.ZS": 0.926, "wdi-IP.IDS.NRCT": 0.822, "wdi2-SL.SLF.0714.FE.ZS": 0.118, "hdr-110806": 0.842, "ndgain-id_ecos_01-score": 0.94, "ihme-acute-myeloid-leukemia": 0.797}, "categories": {"Digestive diseases": 0.554, "Headache disorders": 0.955, "Policy responses": 0.223, "Cardiovascular diseases": 0.947}}}