{"wdi2-SI.POV.MDIM": {"data": {"2014": {"DOM": 29.2, "GNB": 57.8}, "2010": {"DOM": 35.4, "GNB": 65.1}, "2011": {"DOM": 34.3}, "2012": {"DOM": 34.9}, "2013": {"DOM": 33.9}, "2015": {"DOM": 25.5}, "2016": {"DOM": 23.1, "MDV": 28.4}, "2017": {"DOM": 20.9}, "2018": {"DOM": 18.8, "SYC": 31.99}, "2019": {"DOM": 16.4}, "recentValue": {"DOM": 16.4, "GNB": 57.8, "MDV": 28.4, "SYC": 31.99}, "recentYear": {"DOM": "2019", "GNB": "2014", "MDV": "2016", "SYC": "2018"}}, "def": "The percentage of people who are multidimensionally poor", "name": "Multidimensional poverty headcount ratio", "source": "Government statistical agencies. Data for EU countires are from the EUROSTAT", "dataset": "Government statistical agencies. Data for EU countires are from the EUROSTAT", "category": "Poverty", "subcategory": "Multidimensional poverty", "link": "https://data.worldbank.org/indicator/wdi2-SI.POV.MDIM", "dim": "% of total population", "priority": "1.0", "units": "% of total population"}, "confidenceIntervals": {"2014": {"GNB": 57.8}, "2010": {}, "2011": {}, "2012": {}, "2013": {}, "2015": {}, "2016": {}, "2017": {}, "2018": {}, "2019": {}, "recentValue": {}}, "featureImportances": {"indicators": {"wdi-IC.FRM.TRNG.ZS": 0.931, "hdr-38406": 0.956, "wdi-AG.LND.PRCP.MM": 0.733, "key-hdr-137506": 0.552, "wdi2-SE.PRM.NINT.MA.ZS": 0.803, "paris-7": 0.164, "unicef-m8": 0.356, "unicef-e6": 0.659, "paris-62": 0.486, "ihme-unintentional-injuries": 0.186}, "categories": {"Cirrhosis and other chronic liver diseases": 0.941, "Economic Policy & Debt": 0.641, "Self-harm": 0.42, "World Bank, International Debt Statistics.": 0.979}}}