{"wdi-SL.UEM.ADVN.ZS": {"data": {"2014": {"BLZ": 6.369999886, "CYM": 2.809999943, "COM": 12.18999958, "DOM": 5.699999809, "MUS": 7.119999886, "FSM": 5.860000134, "PLW": 0.620000005, "SYC": 3.309999943, "TTO": 1.620000005}, "1995": {"SGP": 2.220000029}, "1996": {"SGP": 3.029999971}, "1997": {"BRB": 2.720000029, "SGP": 0.800000012}, "1998": {"SGP": 1.049999952}, "2000": {"BMU": 1.730000019, "DOM": 5.340000153, "PLW": 2.170000076}, "2001": {"DOM": 5.739999771, "MUS": 5.96999979, "SGP": 0.970000029}, "2002": {"DOM": 5.75, "MUS": 4.559999943, "SGP": 1.840000033}, "2003": {"BRB": 5.21999979, "DOM": 5.869999886, "MUS": 3.130000114, "SGP": 2.160000086}, "2004": {"COM": 4.110000134, "DOM": 5.019999981, "MUS": 3.420000076}, "2005": {"BLZ": 5.21999979, "DOM": 4.880000114, "FJI": 1.850000024, "MUS": 5.260000229}, "2006": {"CUB": 0.689999998, "DOM": 4.409999847, "MUS": 3.319999933, "SGP": 3.680000067, "VUT": 4.670000076}, "2007": {"CUB": 0.560000002, "DOM": 3.440000057, "MUS": 4.519999981, "SGP": 3.410000086}, "2008": {"CUB": 0.400000006, "DOM": 3.170000076, "MUS": 2.700000048, "SGP": 3.769999981}, "2009": {"BMU": 2.819999933, "CUB": 0.479999989, "DOM": 3.329999924, "MDV": 16.82999992, "MUS": 3.319999933, "SGP": 3.839999914}, "2010": {"BMU": 2.329999924, "CUB": 1.450000048, "DOM": 4.300000191, "MUS": 3.589999914, "PNG": 2.380000114, "SGP": 2.829999924, "TLS": 6.670000076, "TTO": 1.720000029}, "2011": {"BHR": 2.5, "CYM": 3.910000086, "DOM": 5.0, "FJI": 6.760000229, "SGP": 2.630000114, "TTO": 1.74000001}, "2012": {"BHR": 2.460000038, "BLZ": 9.68999958, "BMU": 4.369999886, "CYM": 4.150000095, "DOM": 4.130000114, "HTI": 26.79999924, "MUS": 7.010000229, "WSM": 2.599999905, "SGP": 2.75999999, "TTO": 1.669999957}, "2013": {"BLZ": 5.829999924, "CYM": 2.690000057, "DOM": 3.710000038, "MUS": 6.679999828, "SGP": 2.74000001, "SLB": 0.460000008, "TLS": 3.74000001, "TTO": 2.210000038}, "2015": {"BRB": 5.230000019, "BLZ": 5.349999905, "CPV": 20.12000084, "CYM": 2.519999981, "DOM": 6.119999886, "KIR": 2.220000029, "MUS": 8.130000114, "SYC": 3.660000086, "SGP": 3.720000029, "TTO": 1.820000052}, "2016": {"BRB": 4.559999943, "BLZ": 5.400000095, "DOM": 4.619999886, "FJI": 5.019999981, "MDV": 3.529999971, "MUS": 7.849999905, "SYC": 3.24000001, "SUR": 3.609999895, "TLS": 6.139999866, "TTO": 2.349999905, "TUV": 2.450000048}, "2017": {"BRB": 4.079999924, "BLZ": 3.900000095, "CPV": 10.92000008, "DOM": 5.139999866, "MUS": 7.309999943, "WSM": 7.670000076, "SYC": 3.220000029, "SGP": 4.119999886, "LCA": 14.28999996}, "2018": {"BRB": 5.210000038, "CPV": 6.190000057, "DOM": 3.75, "GUY": 4.949999809, "MUS": 7.03000021, "SYC": 2.539999962, "LCA": 7.710000038, "TON": 2.49000001}, "2019": {"BRB": 4.170000076, "CPV": 7.130000114, "DOM": 5.460000038, "MUS": 6.03000021, "SYC": 1.980000019, "LCA": 9.319999695}, "1994": {"BHS": 7.239999771, "SGP": 3.039999962}, "recentValue": {"ATG": "No Data", "ABW": "No Data", "BHS": 7.239999771, "BMU": 4.369999886, "BHR": 2.460000038, "BRB": 4.170000076, "BLZ": 3.900000095, "VGB": "No Data", "CPV": 7.130000114, "CYM": 2.519999981, "COM": 12.18999958, "CUB": 1.450000048, "CUW": "No Data", "DMA": "No Data", "DOM": 5.460000038, "FJI": 5.019999981, "GRD": "No Data", "GNB": "No Data", "GUY": 4.949999809, "HTI": 26.79999924, "JAM": "No Data", "KIR": 2.220000029, "MDV": 3.529999971, "MHL": "No Data", "MUS": 6.03000021, "FSM": 5.860000134, "NRU": "No Data", "PLW": 0.620000005, "PNG": 2.380000114, "WSM": 7.670000076, "STP": "No Data", "SYC": 1.980000019, "SGP": 4.119999886, "SXM": "No Data", "SLB": 0.460000008, "KNA": "No Data", "VCT": "No Data", "LCA": 9.319999695, "SUR": 3.609999895, "TLS": 6.139999866, "TTO": 2.349999905, "TON": 2.49000001, "TUV": 2.450000048, "TCA": "No Data", "VUT": 4.670000076, "AIA": "No Data", "COK": "No Data", "MSR": "No Data", "TKL": "No Data", "NIU": "No Data"}, "recentYear": {"ATG": "Any years", "ABW": "Any years", "BHS": "1994", "BMU": "2012", "BHR": "2012", "BRB": "2019", "BLZ": "2017", "VGB": "Any years", "CPV": "2019", "CYM": "2015", "COM": "2014", "CUB": "2010", "CUW": "Any years", "DMA": "Any years", "DOM": "2019", "FJI": "2016", "GRD": "Any years", "GNB": "Any years", "GUY": "2018", "HTI": "2012", "JAM": "Any years", "KIR": "2015", "MDV": "2016", "MHL": "Any years", "MUS": "2019", "FSM": "2014", "NRU": "Any years", "PLW": "2014", "PNG": "2010", "WSM": "2017", "STP": "Any years", "SYC": "2019", "SGP": "2017", "SXM": "Any years", "SLB": "2013", "KNA": "Any years", "VCT": "Any years", "LCA": "2019", "SUR": "2016", "TLS": "2016", "TTO": "2016", "TON": "2018", "TUV": "2016", "TCA": "Any years", "VUT": "2006", "AIA": "Any years", "COK": "Any years", "MSR": "Any years", "TKL": "Any years", "NIU": "Any years"}}, "def": "The percentage of the labor force with an advanced level of education who are unemployed. Advanced education comprises short-cycle tertiary education, a bachelor\u2019s degree or equivalent education level, a master\u2019s degree or equivalent education level, or doctoral degree or equivalent education level according to the International Standard Classification of Education 2011 (ISCED 2011).", "name": "Unemployment with advanced education", "source": "International Labour Organization, ILOSTAT database. Data retrieved on January 29, 2021.", "dataset": "International Labour Organization, ILOSTAT database. Data retrieved on January 29, 2021.", "category": "Social Protection & Labor", "subcategory": "Unemployment", "link": "https://data.worldbank.org/indicator/wdi-SL.UEM.ADVN.ZS", "dim": "% of total labor force with advanced education", "priority": "1.0", "units": "% of total labor force with advanced education"}}